odoo10_addon_sale_order_project-10.0.1.0.0.99.dev4-py2.7-nspkg.pth
odoo/addons/sale_order_project/README.rst
odoo/addons/sale_order_project/__init__.py
odoo/addons/sale_order_project/__manifest__.py
odoo/addons/sale_order_project/i18n/es.po
odoo/addons/sale_order_project/i18n/pt.po
odoo/addons/sale_order_project/i18n/pt_BR.po
odoo/addons/sale_order_project/i18n/sale_order_project.pot
odoo/addons/sale_order_project/i18n/sl.po
odoo/addons/sale_order_project/models/__init__.py
odoo/addons/sale_order_project/models/sale.py
odoo/addons/sale_order_project/static/description/icon.png
odoo/addons/sale_order_project/tests/__init__.py
odoo/addons/sale_order_project/tests/test_sale_order_project.py
odoo/addons/sale_order_project/views/sale_view.xml
odoo10_addon_sale_order_project-10.0.1.0.0.99.dev4.dist-info/METADATA
odoo10_addon_sale_order_project-10.0.1.0.0.99.dev4.dist-info/RECORD
odoo10_addon_sale_order_project-10.0.1.0.0.99.dev4.dist-info/WHEEL
odoo10_addon_sale_order_project-10.0.1.0.0.99.dev4.dist-info/namespace_packages.txt
odoo10_addon_sale_order_project-10.0.1.0.0.99.dev4.dist-info/top_level.txt
